Reef_Vision/__init__.py
Reef_Vision/apps.py
Reef_Vision/camera.py
Reef_Vision/classify.py
Reef_Vision/classify_server.py
Reef_Vision/detect.py
Reef_Vision/detect_server.py
Reef_Vision/svg.py
Reef_Vision/tpu_cam.py
Reef_Vision/utils.py
Reef_Vision/CameraManager/TPUCameraManager.py
Reef_Vision/CameraManager/__init__.py
Reef_Vision/CameraManager/ggstreamer.py
Reef_Vision/CameraManager/gst.py
Reef_Vision/CameraManager/gstreamer.py
Reef_Vision/models/field_labels.txt
Reef_Vision/models/mobilenet_v2_edgetpu_red.tflite
Reef_Vision/streaming/__init__.py
Reef_Vision/streaming/server.py
Reef_Vision/streaming/assets/bulma.css
Reef_Vision/streaming/assets/index.html
Reef_Vision/streaming/assets/index_release.html
Reef_Vision/streaming/assets/messages.proto
Reef_Vision/streaming/assets/old.html
Reef_Vision/streaming/assets/protobuf.min.js
Reef_Vision/streaming/assets/settings.html
Reef_Vision/streaming/assets/test.html
Reef_Vision/streaming/assets/ws_client.js
Reef_Vision/streaming/assets/broadway/Decoder.js
Reef_Vision/streaming/assets/broadway/LICENSE
Reef_Vision/streaming/assets/broadway/Player.js
Reef_Vision/streaming/assets/broadway/YUVCanvas.js
Reef_Vision/streaming/assets/css/jquery-ui.css
Reef_Vision/streaming/assets/css/orange-bulma.css
Reef_Vision/streaming/assets/css/orange-core.css
Reef_Vision/streaming/assets/images/favicon.png
Reef_Vision/streaming/assets/images/profile.svg
Reef_Vision/streaming/assets/images/logo/logo-clear.svg
Reef_Vision/streaming/assets/images/logo/logo-grey.svg
Reef_Vision/streaming/assets/images/logo/logo-white.svg
Reef_Vision/streaming/assets/images/logo/orange-grey.svg
Reef_Vision/streaming/assets/images/logo/orange-icon.svg
Reef_Vision/streaming/assets/images/svgs/chest.svg
Reef_Vision/streaming/assets/images/svgs/dive_down.svg
Reef_Vision/streaming/assets/images/svgs/lady.svg
Reef_Vision/streaming/assets/images/svgs/shark_wifi.svg
Reef_Vision/streaming/assets/images/svgs/test.svg
Reef_Vision/streaming/assets/js/color_picker.js
Reef_Vision-0.0.25.dist-info/METADATA
Reef_Vision-0.0.25.dist-info/WHEEL
Reef_Vision-0.0.25.dist-info/entry_points.txt
Reef_Vision-0.0.25.dist-info/top_level.txt
Reef_Vision-0.0.25.dist-info/RECORD
