Metadata-Version: 2.1
Name: Reef-Vision
Version: 0.0.25
Summary: FRC Reef Vision API
Home-page: UNKNOWN
Author: Danny Dasilva
Author-email: dannydasilva.solutions@gmail.com
License: Apache 2
Platform: UNKNOWN
Requires-Python: >=3.5.3
Requires-Dist: numpy (>=1.12.1)
Requires-Dist: Pillow (>=4.0.0)
Requires-Dist: pygobject (>=3.22.0)
Requires-Dist: protobuf (>=3.0.0)
Requires-Dist: edgetpu
Requires-Dist: littleutils
Requires-Dist: requests
